{
  "recommendations": [
    {
      "title": "Enhance BRSR and GRI ESG Disclosure for FY26",
      "description": "Commission third-party assurance for BRSR and GRI disclosures to meet SEBI FY26 deadlines by 2026-05-30, mitigating risk of ₹150-300 Cr cost of capital increase due to regulatory scrutiny and trading restrictions.",
      "type": "compliance",
      "responsible_party": "Head of Sustainability Reporting",
      "framework_section": "BRSR:P6:Q14, GRI:102-16",
      "deadline": "2026-05-30",
      "estimated_budget": "₹1-2 Cr",
      "profitability_link": "Avoid ₹150-300 Cr annual cost of capital increase from +20-40 bps rise",
      "priority": "CRITICAL",
      "urgency": "immediate",
      "estimated_impact": "High",
      "risk_of_inaction": 10,
      "roi_percentage": 500.0,
      "payback_months": 1.0,
      "peer_benchmark": "Tata Power enhanced ESG disclosures leading to P/E rerating"
    },
    {
      "title": "Monitor Regulatory Mandates and Energy Price Shocks",
      "description": "Implement a monitoring system to track regulatory mandates with compliance deadlines ≤24 months and energy price shocks ≥25% YoY; escalate to board if thresholds breached within 6 months to proactively manage transition risks.",
      "type": "operational",
      "responsible_party": "Chief Risk Officer",
      "framework_section": "BRSR:P6:Q14",
      "deadline": "2026-10-13",
      "estimated_budget": "₹0.5-1 Cr",
      "profitability_link": "Mitigate potential ₹50-100 Cr losses from unanticipated regulatory penalties or energy cost spikes",
      "priority": "HIGH",
      "urgency": "short_term",
      "estimated_impact": "Medium",
      "risk_of_inaction": 6,
      "roi_percentage": 200.0,
      "payback_months": 6.0,
      "peer_benchmark": "Competitors maintain active regulatory and market risk monitoring to avoid penalties"
    }
  ],
  "do_nothing": false,
  "gate_reason": "",
  "generator_count": 2,
  "validated_count": 2,
  "priority_matrix": {
    "immediate_high": [
      {
        "index": 0,
        "title": "Enhance BRSR and GRI ESG Disclosure for FY26",
        "type": "compliance",
        "roi": 500.0,
        "budget": "₹1-2 Cr"
      }
    ],
    "immediate_low": [
      {
        "index": 1,
        "title": "Monitor Regulatory Mandates and Energy Price Shocks",
        "type": "operational",
        "roi": 200.0,
        "budget": "₹0.5-1 Cr"
      }
    ],
    "deferred_high": [],
    "deferred_low": []
  },
  "recommendation_rankings": {
    "cfo": [
      0,
      1
    ],
    "ceo": [
      1,
      0
    ],
    "esg-analyst": [
      0,
      1
    ]
  }
}