{
  "perspective": "cfo",
  "headline": "₹0-50 Cr at risk (sentiment-driven, not operational) — Quant Small Cap Fund increases stake in ICICI Bank, signaling moderate governance confidence",
  "impact_grid": {
    "financial": "LOW",
    "regulatory": "LOW",
    "strategic": "MEDIUM"
  },
  "what_matters": [
    "BRSR, GRI, DJSI, ESRS frameworks referenced but no direct regulatory trigger or penalty.",
    "No P/E compression or margin erosion; revenue at risk is negligible.",
    "No material impact on cost of capital or fund flows; possible marginal improvement in perception."
  ],
  "action": [
    "No action required — monitor quarterly"
  ],
  "materiality": "LOW",
  "do_nothing": true,
  "active_impact_dimensions": [
    "financial",
    "regulatory"
  ],
  "full_insight": null
}