{
  "paths": [
    {
      "nodes": [
        "Transparency & Disclosure",
        "BRSR",
        "ICICI Bank"
      ],
      "edges": [
        "triggersFramework",
        "regulatoryContagion"
      ],
      "hops": 2,
      "relationship_type": "regulatoryContagion",
      "impact_score": 0.48,
      "explanation": "Transparency & Disclosure triggers BRSR disclosure obligation for ICICI Bank"
    },
    {
      "nodes": [
        "Transparency & Disclosure",
        "GRI",
        "ICICI Bank"
      ],
      "edges": [
        "triggersFramework",
        "regulatoryContagion"
      ],
      "hops": 2,
      "relationship_type": "regulatoryContagion",
      "impact_score": 0.48,
      "explanation": "Transparency & Disclosure triggers GRI disclosure obligation for ICICI Bank"
    },
    {
      "nodes": [
        "Transparency & Disclosure",
        "ESRS",
        "ICICI Bank"
      ],
      "edges": [
        "triggersFramework",
        "regulatoryContagion"
      ],
      "hops": 2,
      "relationship_type": "regulatoryContagion",
      "impact_score": 0.48,
      "explanation": "Transparency & Disclosure triggers ESRS disclosure obligation for ICICI Bank"
    },
    {
      "nodes": [
        "McKinsey Three Horizons",
        "Risk Management",
        "Financials/Banking",
        "ICICI Bank"
      ],
      "edges": [
        "indirectImpact",
        "indirectImpact",
        "industrySpillover"
      ],
      "hops": 3,
      "relationship_type": "industrySpillover",
      "impact_score": 0.2,
      "explanation": "McKinsey Three Horizons -> Risk Management -> Financials/Banking -> ICICI Bank"
    }
  ]
}