{
  "recommendations": [
    {
      "title": "Enhance BRSR and GRI Disclosure Quality",
      "description": "Commission a third-party assurance of BRSR and GRI disclosures for FY26 to close gaps and match JSW Energy's ESG reporting quality, avoiding ₹45 Cr cost of capital increase. Responsible teams to submit assured disclosures by 2026-05-30 to meet SEBI and BRSR requirements.",
      "type": "compliance",
      "responsible_party": "Head of Sustainability Reporting",
      "framework_section": "BRSR:P6:Q14, GRI:102-56",
      "deadline": "2026-05-30",
      "estimated_budget": "₹1-2 Cr",
      "profitability_link": "Avoid ₹45 Cr capital cost increase from higher funding costs due to SEBI scrutiny and investor outflows",
      "priority": "CRITICAL",
      "urgency": "immediate",
      "estimated_impact": "High",
      "risk_of_inaction": 10,
      "roi_percentage": 500.0,
      "payback_months": 1.0,
      "peer_benchmark": "JSW Energy enhanced disclosures to maintain cost of capital advantage"
    },
    {
      "title": "Monitor Energy Price Shock and Regulatory Mandates",
      "description": "Implement a monitoring system to track energy price changes (threshold: ≥25% YoY increase) and regulatory mandates with compliance deadlines within 24 months. Escalate to the Risk Committee if thresholds are breached to enable timely hedging or diversification strategies, mitigating transition and economic risks.",
      "type": "operational",
      "responsible_party": "Chief Risk Officer",
      "framework_section": "BRSR:P7:Q18",
      "deadline": "2026-07-15",
      "estimated_budget": "₹0.5-1 Cr",
      "profitability_link": "Mitigate potential ₹20-40 Cr losses from unhedged energy price shocks and regulatory penalties",
      "priority": "HIGH",
      "urgency": "short_term",
      "estimated_impact": "Medium",
      "risk_of_inaction": 6,
      "roi_percentage": 200.0,
      "payback_months": 6.0,
      "peer_benchmark": "Competitors like Tata Power actively monitor and hedge energy price risks"
    }
  ],
  "do_nothing": false,
  "gate_reason": "",
  "generator_count": 2,
  "validated_count": 2,
  "priority_matrix": {
    "immediate_high": [
      {
        "index": 0,
        "title": "Enhance BRSR and GRI Disclosure Quality",
        "type": "compliance",
        "roi": 500.0,
        "budget": "₹1-2 Cr"
      }
    ],
    "immediate_low": [
      {
        "index": 1,
        "title": "Monitor Energy Price Shock and Regulatory Mandates",
        "type": "operational",
        "roi": 200.0,
        "budget": "₹0.5-1 Cr"
      }
    ],
    "deferred_high": [],
    "deferred_low": []
  },
  "recommendation_rankings": {
    "cfo": [
      0,
      1
    ],
    "ceo": [
      1,
      0
    ],
    "esg-analyst": [
      0,
      1
    ]
  }
}